jsonrescue/__init__.py
jsonrescue/custom_schema.py
jsonrescue/json_rescue.py
jsonrescue/parser.py
jsonrescue-1.0.4.dist-info/METADATA
jsonrescue-1.0.4.dist-info/WHEEL
jsonrescue-1.0.4.dist-info/top_level.txt
jsonrescue-1.0.4.dist-info/RECORD
