Metadata-Version: 2.2
Name: jsonrescue
Version: 1.0.4
Summary: A library to parse and repair malformed JSON-like text.
Home-page: https://github.com/jme900/jsonrescue
Author: Jesse English
Author-email: jme900@gmail.com
License: MIT
Classifier: Programming Language :: Python :: 3
Classifier: License :: OSI Approved :: MIT License
Classifier: Operating System :: OS Independent
Requires-Python: >=3.7
Requires-Dist: regex
Dynamic: author
Dynamic: author-email
Dynamic: classifier
Dynamic: description
Dynamic: description-content-type
Dynamic: home-page
Dynamic: license
Dynamic: requires-dist
Dynamic: requires-python
Dynamic: summary
